README.md
setup.py
pulumi_sdm/__init__.py
pulumi_sdm/_inputs.py
pulumi_sdm/_utilities.py
pulumi_sdm/account.py
pulumi_sdm/account_attachment.py
pulumi_sdm/get_account.py
pulumi_sdm/get_account_attachment.py
pulumi_sdm/get_node.py
pulumi_sdm/get_remote_identity.py
pulumi_sdm/get_remote_identity_group.py
pulumi_sdm/get_resource.py
pulumi_sdm/get_role.py
pulumi_sdm/get_secret_store.py
pulumi_sdm/get_ssh_ca_pubkey.py
pulumi_sdm/node.py
pulumi_sdm/outputs.py
pulumi_sdm/provider.py
pulumi_sdm/pulumi-plugin.json
pulumi_sdm/py.typed
pulumi_sdm/remote_identity.py
pulumi_sdm/resource.py
pulumi_sdm/role.py
pulumi_sdm/secret_store.py
pulumi_sdm.egg-info/PKG-INFO
pulumi_sdm.egg-info/SOURCES.txt
pulumi_sdm.egg-info/dependency_links.txt
pulumi_sdm.egg-info/not-zip-safe
pulumi_sdm.egg-info/requires.txt
pulumi_sdm.egg-info/top_level.txt
pulumi_sdm/config/__init__.py
pulumi_sdm/config/vars.py